{
  "name": "HK Relay",
  "interface": "eth0",
  "period": "2026-06-15 至 2026-07-14",
  "quota_gb": 250.0,
  "quota_bytes": 268435456000,
  "billing_cycle_start_day": 15,
  "billing_mode": "bidirectional",
  "cycle_rx_bytes": 2869739627,
  "cycle_tx_bytes": 2474413484,
  "cycle_total_bytes": 5344153111,
  "month_rx_bytes": 2869739627,
  "month_tx_bytes": 2474413484,
  "month_total_bytes": 5344153111,
  "today_rx_bytes": 15872174,
  "today_tx_bytes": 3949913,
  "today_total_bytes": 19822087,
  "updated_at": "2026-06-28T21:50:01.813226Z",
  "source": "vnstat"
}
