{
  "name": "HK Relay",
  "interface": "eth0",
  "period": "2026-06-15 至 2026-07-14",
  "quota_gb": 250.0,
  "quota_bytes": 268435456000,
  "billing_cycle_start_day": 15,
  "billing_mode": "bidirectional",
  "cycle_rx_bytes": 2849171399,
  "cycle_tx_bytes": 2469691002,
  "cycle_total_bytes": 5318862401,
  "month_rx_bytes": 2849171399,
  "month_tx_bytes": 2469691002,
  "month_total_bytes": 5318862401,
  "today_rx_bytes": 1476154693,
  "today_tx_bytes": 1369298720,
  "today_total_bytes": 2845453413,
  "updated_at": "2026-06-28T17:30:01.039911Z",
  "source": "vnstat"
}
