{
  "name": "HK Relay",
  "interface": "eth0",
  "period": "2026-06-15 至 2026-07-14",
  "quota_gb": 250.0,
  "quota_bytes": 268435456000,
  "billing_cycle_start_day": 15,
  "billing_mode": "bidirectional",
  "cycle_rx_bytes": 4601755942,
  "cycle_tx_bytes": 4132783698,
  "cycle_total_bytes": 8734539640,
  "month_rx_bytes": 4601755942,
  "month_tx_bytes": 4132783698,
  "month_total_bytes": 8734539640,
  "today_rx_bytes": 1747888489,
  "today_tx_bytes": 1662320127,
  "today_total_bytes": 3410208616,
  "updated_at": "2026-06-29T16:40:01.723662Z",
  "source": "vnstat"
}
